{
  "schema_version": 1,
  "sprint_id": "S9a",
  "gate_id": "GATE-CP5-D04-resolution",
  "audit_id": "S9a-d04-stale-reference-audit",
  "status": "completed",
  "generated_on": "2026-05-16",
  "subject_unit": "D04",
  "summary": {
    "active_authored_target_exercise_citations": 0,
    "protected_external_exam_question_citations": 1,
    "protected_machine_deprecated_unit_records": 2,
    "term_reverse_index_mentions": 2,
    "historical_or_provenance_mentions_allowed": true,
    "active_source_cleanup_required": false
  },
  "active_source_findings": [
    {
      "path": "references/authored/course-target-exercises.json",
      "status": "cleaned",
      "remaining_d04_required_skills": 0,
      "remaining_d04_new_skills_introduced": 0,
      "cleanup": "Removed D04 from target exercise 2.1.3 because successor units A16, A17, D11, D12, and D27 were already present."
    }
  ],
  "protected_external_findings": [
    {
      "path": "references/external/exam-questions.json",
      "status": "preserved_read_only",
      "remaining_citations": 1,
      "reason": "External exam extraction is machine-refreshed input and must not be hand-mutated in S9a."
    }
  ],
  "protected_machine_findings": [
    {
      "path": "references/machine/micro-teaching-units.json",
      "status": "intentional_deprecated_record",
      "reason": "D04 remains as a deprecated catalog record with replacement pointers."
    },
    {
      "path": "references/machine/micro-teaching-units.md",
      "status": "intentional_deprecated_record",
      "reason": "Markdown projection mirrors the CLI-written deprecated catalog record."
    },
    {
      "path": "references/machine/begrippen.json",
      "status": "derived_reverse_index_mention",
      "reason": "The term reverse index can mention deprecated teaching units; it is not an active promotion dependency."
    },
    {
      "path": "references/machine/begrippen.md",
      "status": "derived_reverse_index_mention",
      "reason": "The term markdown projection can mention deprecated teaching units; it is not an active promotion dependency."
    }
  ],
  "historical_and_generated_policy": {
    "allowed_categories": [
      "S9 and S9a sprint artifacts",
      "CP-5 review and gate artifacts",
      "earlier R2/R5 provenance records",
      "roadmap snapshots",
      "generated reports before regeneration",
      "RAG chunks before regeneration"
    ],
    "required_label": "historical, generated, deprecated, or non-authoritative provenance only",
    "not_allowed": [
      "active target-exercise requirement on D04",
      "new D04 prerequisite edge",
      "student-facing promotion dependency"
    ]
  },
  "conclusion": {
    "d04_active_target_exercise_dependency_removed": true,
    "d04_external_exam_citation_preserved_read_only": true,
    "d04_deprecated_machine_record_intentional": true,
    "d04_prerequisite_edge_added": false,
    "exercise_promotion_authorized": false
  }
}
